{"em":[{"location":{"latitude":51.41,"longitude":5.53}},{"location":{"latitude":51.66,"longitude":5.11}}],"bites":[{"location":{"latitude":51.92,"longitude":4.1}},{"location":{"latitude":52.99,"longitude":6.58}},{"location":{"latitude":53.07,"longitude":6.2}},{"location":{"latitude":51.68,"longitude":3.71}},{"location":{"latitude":51.27,"longitude":4.05}},{"location":{"latitude":52.16,"longitude":6.3}},{"location":{"latitude":52.74,"longitude":6.8}},{"location":{"latitude":51.97,"longitude":4.17}}],"other":[],"fever":[]}