{"em":[{"location":{"latitude":52.42,"longitude":6.89}}],"bites":[{"location":{"latitude":52.3,"longitude":5.2}},{"location":{"latitude":53.13,"longitude":6.06}},{"location":{"latitude":53.08,"longitude":6.62}},{"location":{"latitude":51.93,"longitude":5.1}},{"location":{"latitude":51.64,"longitude":4.47}},{"location":{"latitude":51.53,"longitude":4.29}},{"location":{"latitude":52.5,"longitude":6.23}},{"location":{"latitude":53.22,"longitude":5.91}},{"location":{"latitude":51.63,"longitude":4.28}},{"location":{"latitude":51.68,"longitude":3.71}},{"location":{"latitude":53.45,"longitude":5.78}},{"location":{"latitude":52.19,"longitude":5.21}},{"location":{"latitude":51.59,"longitude":4.58}},{"location":{"latitude":52.4,"longitude":5.84}},{"location":{"latitude":51.63,"longitude":5.08}}],"other":[],"fever":[]}