{"em":[],"bites":[{"location":{"latitude":52.51,"longitude":6.45}},{"location":{"latitude":52.18,"longitude":5.17}},{"location":{"latitude":51.99,"longitude":5.83}},{"location":{"latitude":52.29,"longitude":6.53}},{"location":{"latitude":52.15,"longitude":6.39}},{"location":{"latitude":52.11,"longitude":6.41}},{"location":{"latitude":51.8,"longitude":3.89}},{"location":{"latitude":52.5,"longitude":4.59}},{"location":{"latitude":52.86,"longitude":6.88}},{"location":{"latitude":52.94,"longitude":7.16}},{"location":{"latitude":52.66,"longitude":5.05}},{"location":{"latitude":51.71,"longitude":6.07}},{"location":{"latitude":51.96,"longitude":4.5}},{"location":{"latitude":51.63,"longitude":5.07}},{"location":{"latitude":51.94,"longitude":4.44}},{"location":{"latitude":52.34,"longitude":4.9}},{"location":{"latitude":52.57,"longitude":6.11}},{"location":{"latitude":51.96,"longitude":5.69}},{"location":{"latitude":52.45,"longitude":6}},{"location":{"latitude":51.67,"longitude":3.7}},{"location":{"latitude":51.79,"longitude":5.85}},{"location":{"latitude":52.25,"longitude":5.12}},{"location":{"latitude":52.22,"longitude":6.87}},{"location":{"latitude":51.31,"longitude":5.37}},{"location":{"latitude":52.41,"longitude":5.85}},{"location":{"latitude":52.2,"longitude":6.29}},{"location":{"latitude":51.64,"longitude":5.13}},{"location":{"latitude":52.21,"longitude":5.85}},{"location":{"latitude":51.23,"longitude":5.7}}],"other":[{"location":{"latitude":52.56,"longitude":5.03}},{"location":{"latitude":52.34,"longitude":4.62}},{"location":{"latitude":51.55,"longitude":5.43}},{"location":{"latitude":53.17,"longitude":6.66}}],"fever":[]}