{"em":[],"bites":[{"location":{"latitude":52.51,"longitude":6.38}},{"location":{"latitude":51.75,"longitude":5.51}},{"location":{"latitude":51.9,"longitude":6.14}},{"location":{"latitude":52.43,"longitude":4.63}},{"location":{"latitude":51.73,"longitude":5.58}},{"location":{"latitude":51.68,"longitude":4.2}},{"location":{"latitude":51.47,"longitude":5.7}},{"location":{"latitude":53.33,"longitude":6.43}},{"location":{"latitude":52.02,"longitude":6.5}},{"location":{"latitude":52.1,"longitude":6.06}}],"other":[{"location":{"latitude":53,"longitude":6.95}},{"location":{"latitude":51.81,"longitude":5.74}},{"location":{"latitude":51.7,"longitude":5.33}},{"location":{"latitude":51.43,"longitude":4.32}},{"location":{"latitude":50.33,"longitude":5.56}}],"fever":[]}