{"em":[{"location":{"latitude":52.26,"longitude":6.72}}],"bites":{"1":{"location":{"latitude":52.14,"longitude":6.23}},"2":{"location":{"latitude":52.68,"longitude":7.04}},"3":{"location":{"latitude":51.85,"longitude":4.08}},"4":{"location":{"latitude":51.37,"longitude":5.77}},"5":{"location":{"latitude":52.15,"longitude":5.24}},"6":{"location":{"latitude":52.05,"longitude":4.44}},"7":{"location":{"latitude":51.5,"longitude":5.67}},"8":{"location":{"latitude":52.95,"longitude":6.45}},"9":{"location":{"latitude":51.81,"longitude":3.86}},"10":{"location":{"latitude":52.25,"longitude":5.95}},"11":{"location":{"latitude":52.21,"longitude":5.26}},"12":{"location":{"latitude":52.71,"longitude":4.68}},"13":{"location":{"latitude":52.15,"longitude":4.39}},"14":{"location":{"latitude":53.15,"longitude":6.15}}},"other":[],"fever":[]}