{"em":[],"bites":[{"location":{"latitude":52.08,"longitude":5.24}},{"location":{"latitude":52.39,"longitude":4.91}},{"location":{"latitude":53.19,"longitude":6.54}},{"location":{"latitude":52.12,"longitude":5.88}},{"location":{"latitude":50.27,"longitude":5.93}},{"location":{"latitude":52.27,"longitude":5.68}},{"location":{"latitude":52.82,"longitude":6.47}},{"location":{"latitude":51.87,"longitude":4.06}},{"location":{"latitude":52.85,"longitude":5.71}},{"location":{"latitude":51.35,"longitude":6.2}},{"location":{"latitude":52.34,"longitude":4.61}},{"location":{"latitude":51.99,"longitude":5.81}},{"location":{"latitude":52.35,"longitude":5.24}},{"location":{"latitude":51.49,"longitude":5.48}},{"location":{"latitude":52.2,"longitude":5.23}},{"location":{"latitude":51.54,"longitude":3.68}},{"location":{"latitude":52.52,"longitude":4.63}},{"location":{"latitude":52.14,"longitude":6.27}},{"location":{"latitude":52.33,"longitude":4.53}},{"location":{"latitude":52.36,"longitude":4.61}},{"location":{"latitude":51.69,"longitude":3.73}}],"other":[],"fever":[]}