{"em":[],"bites":[{"location":{"latitude":52.05,"longitude":6.39}},{"location":{"latitude":50.83,"longitude":5.77}},{"location":{"latitude":55.43,"longitude":10.69}},{"location":{"latitude":52.31,"longitude":6.11}},{"location":{"latitude":51.92,"longitude":6.24}},{"location":{"latitude":52.92,"longitude":6.26}},{"location":{"latitude":52.35,"longitude":6.65}},{"location":{"latitude":51.95,"longitude":5.38}},{"location":{"latitude":49.68,"longitude":5.51}},{"location":{"latitude":52.9,"longitude":5.04}},{"location":{"latitude":53.17,"longitude":6.51}},{"location":{"latitude":52.19,"longitude":5.25}},{"location":{"latitude":51.8,"longitude":3.87}},{"location":{"latitude":50.77,"longitude":5.95}},{"location":{"latitude":52.2,"longitude":5.91}},{"location":{"latitude":49.53,"longitude":15.24}}],"other":[],"fever":[]}